{
  "shared": {
    "AccentBackgroundDark": "#090909",
    "AccentBackgroundLight": "#EEEFF0",
    "AccentBackgroundSecondaryDark": "#252629",
    "AccentBackgroundSecondaryLight": "#F8F8F9",
    "AccentFrostedGlassTintDark": "#FFFFFF00",
    "AccentFrostedGlassTintLight": "#FFFFFF16",
    "AccentIslandDark": "#18191B",
    "AccentIslandLight": "#FFFFFF",
    "AccentPopupDark": "#252629",
    "AccentPopupLight": "#FFFFFF",
    "AccentProblemTagWeakWarningBackgroundDefaultDark": "#3E4147",
    "AccentProblemTagWeakWarningBackgroundDefaultLight": "#00000022",
    "AccentProblemTagWeakWarningBackgroundHoveredDark": "#323438",
    "AccentProblemTagWeakWarningBackgroundHoveredLight": "#0000002E",
    "AccentProblemTagWeakWarningBackgroundPressedDark": "#252629",
    "AccentProblemTagWeakWarningBackgroundPressedLight": "#00000046",
    "AccentTint_10": "#0870E41A",
    "AccentTint_15": "#0870E426",
    "AccentTint_20": "#0870E433",
    "AccentTint_25": "#0870E440",
    "AccentTint_30": "#0870E44D",
    "AccentTint_40": "#0870E466",
    "AccentTint_5": "#0870E40D",
    "AccentTint_50": "#0870E480",
    "AccentTint_60": "#0870E499",
    "AccentTooltipBackgroundDark": "#323438",
    "AccentTooltipBackgroundLight": "#252629",
    "AccentTooltipTextSecondaryDark": "#FFFFFF85",
    "AccentTooltipTextSecondaryLight": "#FFFFFF9B",
    "Accent_10": "#06090F",
    "Accent_100": "#2A7DEB",
    "Accent_110": "#4B8DEC",
    "Accent_120": "#71A3EF",
    "Accent_130": "#A8C6F4",
    "Accent_140": "#D6E3F9",
    "Accent_150": "#E9EFFC",
    "Accent_160": "#F7F8FE",
    "Accent_20": "#111926",
    "Accent_30": "#18263C",
    "Accent_40": "#1E3455",
    "Accent_50": "#224271",
    "Accent_60": "#225090",
    "Accent_70": "#1D61BA",
    "Accent_80": "#1868CB",
    "Accent_90": "#0870E4",
    "Black": "#000000",
    "BlueBright": "#05A8FA",
    "BlueTint_10": "#0870E41A",
    "BlueTint_15": "#0870E426",
    "BlueTint_20": "#0870E433",
    "BlueTint_25": "#0870E440",
    "BlueTint_30": "#0870E44D",
    "BlueTint_40": "#0870E466",
    "BlueTint_5": "#0870E40D",
    "BlueTint_50": "#0870E480",
    "BlueTint_60": "#0870E499",
    "Blue_10": "#06090F",
    "Blue_100": "#2A7DEB",
    "Blue_110": "#4B8DEC",
    "Blue_120": "#71A3EF",
    "Blue_130": "#A8C6F4",
    "Blue_140": "#D6E3F9",
    "Blue_150": "#E9EFFC",
    "Blue_160": "#F7F8FE",
    "Blue_20": "#111926",
    "Blue_30": "#18263C",
    "Blue_40": "#1E3455",
    "Blue_50": "#224271",
    "Blue_60": "#225090",
    "Blue_70": "#1D61BA",
    "Blue_80": "#1868CB",
    "Blue_90": "#0870E4",
    "DarkTint_13": "#00000022",
    "DarkTint_18": "#0000002E",
    "DarkTint_27": "#00000046",
    "DarkTint_3": "#00000007",
    "DarkTint_45": "#00000073",
    "DarkTint_5": "#0000000C",
    "DarkTint_54": "#0000008B",
    "DarkTint_6": "#00000010",
    "DarkTint_60": "#00000099",
    "DarkTint_63": "#000000A0",
    "DarkTint_9": "#00000018",
    "GreenBright": "#13BF86",
    "GreenTint_10": "#14835E1A",
    "GreenTint_15": "#14835E26",
    "GreenTint_20": "#14835E33",
    "GreenTint_40": "#14835E66",
    "GreenTint_50": "#14835E80",
    "Green_10": "#060A08",
    "Green_100": "#169068",
    "Green_110": "#409D78",
    "Green_120": "#69B090",
    "Green_130": "#A3CEB8",
    "Green_140": "#D2E7DB",
    "Green_150": "#E6F2EA",
    "Green_160": "#F5FAF5",
    "Green_20": "#111B16",
    "Green_30": "#182921",
    "Green_40": "#1F392D",
    "Green_50": "#234939",
    "Green_60": "#255A44",
    "Green_70": "#216F52",
    "Green_80": "#1E7857",
    "Green_90": "#14835E",
    "HudHighlightResizeBorderCenterHoveredDark": "#0870E44D",
    "HudHighlightResizeBorderCenterHoveredLight": "#0870E44D",
    "HudHighlightResizeBorderCenterPressedDark": "#0870E4",
    "HudHighlightResizeBorderCenterPressedLight": "#2A7DEB",
    "HudHighlightResizeBorderEdgeHoveredDark": "#090909",
    "HudHighlightResizeBorderEdgeHoveredLight": "#FFFFFF00",
    "HudHighlightResizeBorderEdgePressedDark": "#0870E40D",
    "HudHighlightResizeBorderEdgePressedLight": "#0870E40D",
    "HudStatusBarTextDefaultDark": "#FFFFFF85",
    "HudStatusBarTextDefaultLight": "#0000008B",
    "HudStatusBarTextHoveredDark": "#FFFFFF85",
    "HudStatusBarTextHoveredLight": "#0000008B",
    "HudStatusBarTextPressedDark": "#FFFFFF85",
    "HudStatusBarTextPressedLight": "#0000008B",
    "LightTint_11": "#FFFFFF1B",
    "LightTint_13": "#FFFFFF21",
    "LightTint_17": "#FFFFFF2C",
    "LightTint_26": "#FFFFFF43",
    "LightTint_35": "#FFFFFF59",
    "LightTint_4": "#FFFFFF0B",
    "LightTint_44": "#FFFFFF6F",
    "LightTint_52": "#FFFFFF85",
    "LightTint_61": "#FFFFFF9B",
    "LightTint_69": "#FFFFFFB1",
    "LightTint_7": "#FFFFFF12",
    "LightTint_72": "#FFFFFFB8",
    "LightTint_75": "#FFFFFFBF",
    "LightTint_9": "#FFFFFF16",
    "MagentaBright": "#F558BB",
    "Neutral_10": "#090909",
    "Neutral_100": "#7A7F86",
    "Neutral_110": "#898E94",
    "Neutral_120": "#9EA3A8",
    "Neutral_130": "#C3C5C9",
    "Neutral_140": "#E0E1E4",
    "Neutral_150": "#EEEFF0",
    "Neutral_160": "#F8F8F9",
    "Neutral_20": "#18191B",
    "Neutral_30": "#252629",
    "Neutral_40": "#323438",
    "Neutral_50": "#3E4147",
    "Neutral_60": "#4C5157",
    "Neutral_70": "#5D636B",
    "Neutral_80": "#646B71",
    "Neutral_90": "#6E747B",
    "OrangeBright": "#FF790D",
    "PurpleBright": "#BC7EFF",
    "PurpleTint_15": "#9D4FCF26",
    "PurpleTint_20": "#9D4FCF33",
    "PurpleTint_40": "#9D4FCF66",
    "Purple_10": "#0B080D",
    "Purple_100": "#A660D4",
    "Purple_110": "#B174D9",
    "Purple_120": "#C08FE0",
    "Purple_130": "#D8B9EC",
    "Purple_140": "#EDDCF5",
    "Purple_150": "#F6EAF9",
    "Purple_160": "#FDF6FD",
    "Purple_20": "#1E1524",
    "Purple_30": "#2F2139",
    "Purple_40": "#412B50",
    "Purple_50": "#55346A",
    "Purple_60": "#6A3D88",
    "Purple_70": "#8646AE",
    "Purple_80": "#9049BE",
    "Purple_90": "#9D4FCF",
    "RedTint_10": "#D732511A",
    "RedTint_15": "#D7325126",
    "RedTint_20": "#D7325133",
    "RedTint_30": "#D732514D",
    "RedTint_50": "#D7325180",
    "Red_10": "#100607",
    "Red_100": "#E1465E",
    "Red_110": "#EC5D6F",
    "Red_120": "#F87C88",
    "Red_130": "#FFB0B5",
    "Red_140": "#FFD8DA",
    "Red_150": "#FFE9EA",
    "Red_160": "#FFF8F8",
    "Red_20": "#291214",
    "Red_30": "#401A1E",
    "Red_40": "#592228",
    "Red_50": "#742831",
    "Red_60": "#922C3B",
    "Red_70": "#B82D46",
    "Red_80": "#C72C49",
    "Red_90": "#D73251",
    "TealBright": "#1AC7BE",
    "Transparent": "#FFFFFF00",
    "VioletBright": "#8A80FF",
    "VioletTint_15": "#685AFB26",
    "VioletTint_20": "#685AFB33",
    "VioletTint_40": "#685AFB66",
    "VioletTint_50": "#685AFB80",
    "Violet_10": "#080810",
    "Violet_100": "#726CF9",
    "Violet_110": "#7F80F9",
    "Violet_120": "#9599F9",
    "Violet_130": "#BDC0FA",
    "Violet_140": "#DEDFFC",
    "Violet_150": "#EEEDFD",
    "Violet_160": "#F9F7FE",
    "Violet_20": "#17172B",
    "Violet_30": "#222342",
    "Violet_40": "#2E2E61",
    "Violet_50": "#3A3982",
    "Violet_60": "#4843A8",
    "Violet_70": "#594CDD",
    "Violet_80": "#604EF3",
    "Violet_90": "#685AFB",
    "White": "#FFFFFF",
    "YellowBright": "#E59408",
    "YellowTint_10": "#9F680C1A",
    "YellowTint_15": "#9F680C26",
    "YellowTint_20": "#9F680C33",
    "YellowTint_40": "#9F680C66",
    "YellowTint_50": "#9F680C80",
    "Yellow_10": "#0C0805",
    "Yellow_100": "#B07203",
    "Yellow_110": "#BD8128",
    "Yellow_120": "#CD984D",
    "Yellow_130": "#E5BF8C",
    "Yellow_140": "#F5DEC2",
    "Yellow_150": "#FCEDDC",
    "Yellow_160": "#FFF8EF",
    "Yellow_20": "#20180C",
    "Yellow_30": "#302412",
    "Yellow_40": "#433016",
    "Yellow_50": "#573D18",
    "Yellow_60": "#6C4B18",
    "Yellow_70": "#865A15",
    "Yellow_80": "#916012",
    "Yellow_90": "#9F680C"
  },
  "dark": {
    "Blue": "#87C3FF",
    "Blue Light": "#ADD1DE",
    "Coral": "#CC7C8A",
    "Cyan": "#82D2CE",
    "Cyan Dark": "#779E9E",
    "LightTint_30": "#FFFFFF4C",
    "LightTint_40": "#FFFFFF66",
    "LightTint_50": "#FFFFFF80",
    "Lime": "#A8CC7C",
    "Orange": "#E09B70",
    "Pink": "#E394DC",
    "Violet": "#AF9CFF",
    "VioletTint_30": "#685AFB4D",
    "Yellow": "#EBC88D"
  },
  "light": {
    "AccentTint_35": "#0870E459",
    "Blue": "#1749BD",
    "BlueTint_35": "#0870E459",
    "Brown": "#664229",
    "DarkTint_30": "#0000004C",
    "Green": "#086E14",
    "GreenTint_25": "#14835E40",
    "GreenTint_5": "#14835E0D",
    "Lime": "#616605",
    "Orange": "#BF4A02",
    "OrangeTint_15": "#BB560426",
    "OrangeTint_20": "#BB560433",
    "OrangeTint_40": "#BB560466",
    "Orange_100": "#C86216",
    "Orange_140": "#FFDAC3",
    "Orange_150": "#FFE8D5",
    "Orange_50": "#5F3513",
    "Orange_60": "#7A4215",
    "Orange_70": "#9C4C11",
    "Pink": "#A31D8D",
    "Plum": "#944A9E",
    "Teal": "#14646E",
    "Teal Dark": "#47676B",
    "TealTint_15": "#097F8E26",
    "TealTint_20": "#097F8E33",
    "TealTint_40": "#097F8E66",
    "Teal_100": "#298A99",
    "Teal_140": "#D2E3E7",
    "Teal_150": "#E8F0F2",
    "Teal_50": "#1C4248",
    "Teal_60": "#1E545C",
    "Teal_70": "#1F6B77",
    "Violet": "#5511BF",
    "VioletTint_25": "#685AFB40",
    "YellowTint_30": "#9F680C4D"
  }
}
